{
    "name": "Hyperframework\\Logging\\LoggerEngine",
    "line": 9,
    "short_desc": "",
    "long_desc": "",
    "hint": null,
    "tags": [],
    "namespace": "Hyperframework\\Logging",
    "file": "\/home\/az\/quickquick\/vendor\/hyperframework\/hyperframework\/lib\/Logging\/LoggerEngine.php",
    "hash": "c6cc3cdedd9a6b9d77c68159fe7833bd507bcf9c",
    "parent": null,
    "modifiers": 0,
    "is_trait": false,
    "is_interface": false,
    "aliases": {
        "Closure": "Closure",
        "Config": "Hyperframework\\Common\\Config",
        "ConfigException": "Hyperframework\\Common\\ConfigException",
        "ClassNotFoundException": "Hyperframework\\Common\\ClassNotFoundException"
    },
    "errors": [],
    "interfaces": [],
    "traits": [],
    "properties": {
        "level": {
            "name": "level",
            "line": 10,
            "short_desc": "",
            "long_desc": "",
            "hint": null,
            "hint_desc": null,
            "tags": [],
            "modifiers": 4,
            "default": null,
            "errors": []
        },
        "logHandler": {
            "name": "logHandler",
            "line": 11,
            "short_desc": "",
            "long_desc": "",
            "hint": null,
            "hint_desc": null,
            "tags": [],
            "modifiers": 4,
            "default": null,
            "errors": []
        }
    },
    "methods": {
        "log": {
            "name": "log",
            "line": 17,
            "short_desc": "",
            "long_desc": "",
            "hint": null,
            "hint_desc": null,
            "tags": [],
            "modifiers": "1",
            "is_by_ref": "",
            "exceptions": [],
            "errors": [],
            "parameters": {
                "level": {
                    "name": "level",
                    "line": 17,
                    "short_desc": "",
                    "long_desc": null,
                    "hint": [
                        [
                            "int",
                            false
                        ]
                    ],
                    "tags": [],
                    "modifiers": "",
                    "default": null,
                    "is_by_ref": false
                },
                "mixed": {
                    "name": "mixed",
                    "line": 17,
                    "short_desc": "",
                    "long_desc": null,
                    "hint": [
                        [
                            "mixed",
                            false
                        ]
                    ],
                    "tags": [],
                    "modifiers": "",
                    "default": null,
                    "is_by_ref": false
                }
            }
        },
        "setLevel": {
            "name": "setLevel",
            "line": 45,
            "short_desc": "",
            "long_desc": "",
            "hint": null,
            "hint_desc": null,
            "tags": [],
            "modifiers": "1",
            "is_by_ref": "",
            "exceptions": [],
            "errors": [],
            "parameters": {
                "level": {
                    "name": "level",
                    "line": 45,
                    "short_desc": "",
                    "long_desc": null,
                    "hint": [
                        [
                            "int",
                            false
                        ]
                    ],
                    "tags": [],
                    "modifiers": "",
                    "default": null,
                    "is_by_ref": false
                }
            }
        },
        "getLevel": {
            "name": "getLevel",
            "line": 52,
            "short_desc": "",
            "long_desc": "",
            "hint": [
                [
                    "int",
                    false
                ]
            ],
            "hint_desc": "",
            "tags": [],
            "modifiers": "1",
            "is_by_ref": "",
            "exceptions": [],
            "errors": [],
            "parameters": []
        },
        "setLogHandler": {
            "name": "setLogHandler",
            "line": 76,
            "short_desc": "",
            "long_desc": "",
            "hint": null,
            "hint_desc": null,
            "tags": [],
            "modifiers": "1",
            "is_by_ref": "",
            "exceptions": [],
            "errors": [],
            "parameters": {
                "logHandler": {
                    "name": "logHandler",
                    "line": 76,
                    "short_desc": "",
                    "long_desc": null,
                    "hint": [
                        [
                            "object",
                            false
                        ]
                    ],
                    "tags": [],
                    "modifiers": "",
                    "default": null,
                    "is_by_ref": false
                }
            }
        },
        "getLogHandler": {
            "name": "getLogHandler",
            "line": 83,
            "short_desc": "",
            "long_desc": "",
            "hint": [
                [
                    "object",
                    false
                ]
            ],
            "hint_desc": "",
            "tags": [],
            "modifiers": "1",
            "is_by_ref": "",
            "exceptions": [],
            "errors": [],
            "parameters": []
        }
    },
    "constants": []
}